MANIFEST.in
requirements.txt
setup.py
ssh2ec2/__init__.py
ssh2ec2.egg-info/PKG-INFO
ssh2ec2.egg-info/SOURCES.txt
ssh2ec2.egg-info/dependency_links.txt
ssh2ec2.egg-info/entry_points.txt
ssh2ec2.egg-info/requires.txt
ssh2ec2.egg-info/top_level.txt