Metadata-Version: 1.0
Name: ssh2ec2
Version: 0.6
Summary: SSH into EC2 instances via tags and metadata filters
Home-page: https://github.com/mikery/ssh2ec2
Author: Mike Ryan
Author-email: mike@awssystemadministration.com
License: MIT
Keywords: amazon,aws,ec2,ssh,cloud,boto
Platform: UNKNOWN
